seed_cluster.cp38-win_amd64.pyd
seed_cluster-0.1.0.dist-info/METADATA
seed_cluster-0.1.0.dist-info/WHEEL
seed_cluster-0.1.0.dist-info/top_level.txt
seed_cluster-0.1.0.dist-info/RECORD
