Metadata-Version: 2.1
Name: seed-cluster
Version: 0.1.0
Summary: seed_cluster
Home-page: UNKNOWN
Author: UNKNOWN
Author-email: UNKNOWN
License: Licence
Keywords: seed_cluster
Platform: any
